[{"kind":"youtube#playlistItem","etag":"Si8nx2kvThjtIxqrlOK5dqOteSo","id":"VVVKZ0djOHBRTzFsdjA0VlhyQnhBX0hnLmVhQXBzOXRqdGJN","snippet":{"publishedAt":"2022-12-07T18:38:25Z","channelId":"UCJgGc8pQO1lv04VXrBxA_Hg","title":"Empresa busca Programador JUNIOR con 4 AÑOS de Experiencia","description":"","thumbnails":{"default":{"url":"https://i.ytimg.com/vi/eaAps9tjtbM/default.jpg","width":120,"height":90},"medium":{"url":"https://i.ytimg.com/vi/eaAps9tjtbM/mqdefault.jpg","width":320,"height":180},"high":{"url":"https://i.ytimg.com/vi/eaAps9tjtbM/hqdefault.jpg","width":480,"height":360},"standard":{"url":"https://i.ytimg.com/vi/eaAps9tjtbM/sddefault.jpg","width":640,"height":480},"maxres":{"url":"https://i.ytimg.com/vi/eaAps9tjtbM/maxresdefault.jpg","width":1280,"height":720}},"channelTitle":"Carlos Azaustre - Aprende JavaScript","playlistId":"UUJgGc8pQO1lv04VXrBxA_Hg","position":0,"resourceId":{"kind":"youtube#video","videoId":"eaAps9tjtbM"},"videoOwnerChannelTitle":"Carlos Azaustre - Aprende JavaScript","videoOwnerChannelId":"UCJgGc8pQO1lv04VXrBxA_Hg"}},{"kind":"youtube#playlistItem","etag":"x68XRqDZoA2xYUWCpF6bMVQSJ6A","id":"VVVKZ0djOHBRTzFsdjA0VlhyQnhBX0hnLlRKcUotV1kzWHhB","snippet":{"publishedAt":"2022-12-05T16:23:00Z","channelId":"UCJgGc8pQO1lv04VXrBxA_Hg","title":"Cómo DESPLEGAR Aplicaciones Web con NEXT.js en FIREBASE HOSTING - Server Side Rendering","description":"Aprende como puedes desplegar aplicaciones web utilizando Server Side Rendering (SSR) con Next.js y React en el nuevo Firebase Hosting\n\nInicia tu aprendizaje en Coderhouse y recibe un 10% adicional con el código CARLOSCODER, haciendo click aquí: https://carlosazaustre.es/coderhouse\n\nTienes este tutorial en formato texto aquí:\n► https://carlosazaustre.es/firebase-hosting-ssr\n\nÚnete a la MEJOR COMUNIDAD de programación y desarrollo web en español. \n► https://carlosazaustre.es/discord \n\nSuscríbete y activa la campanita para no perderte ningún vídeo \n► https://youtube.com/carlosazaustre?sub_confirmation=1","thumbnails":{"default":{"url":"https://i.ytimg.com/vi/TJqJ-WY3XxA/default.jpg","width":120,"height":90},"medium":{"url":"https://i.ytimg.com/vi/TJqJ-WY3XxA/mqdefault.jpg","width":320,"height":180},"high":{"url":"https://i.ytimg.com/vi/TJqJ-WY3XxA/hqdefault.jpg","width":480,"height":360},"standard":{"url":"https://i.ytimg.com/vi/TJqJ-WY3XxA/sddefault.jpg","width":640,"height":480},"maxres":{"url":"https://i.ytimg.com/vi/TJqJ-WY3XxA/maxresdefault.jpg","width":1280,"height":720}},"channelTitle":"Carlos Azaustre - Aprende JavaScript","playlistId":"UUJgGc8pQO1lv04VXrBxA_Hg","position":1,"resourceId":{"kind":"youtube#video","videoId":"TJqJ-WY3XxA"},"videoOwnerChannelTitle":"Carlos Azaustre - Aprende JavaScript","videoOwnerChannelId":"UCJgGc8pQO1lv04VXrBxA_Hg"}},{"kind":"youtube#playlistItem","etag":"M5AuUZ9FdYJ6-71adHZti2Zb1Sk","id":"VVVKZ0djOHBRTzFsdjA0VlhyQnhBX0hnLmtQRFY1cDFDY0dr","snippet":{"publishedAt":"2022-11-30T16:18:00Z","channelId":"UCJgGc8pQO1lv04VXrBxA_Hg","title":"Qué son CONVENTIONAL COMMITS","description":"","thumbnails":{"default":{"url":"https://i.ytimg.com/vi/kPDV5p1CcGk/default.jpg","width":120,"height":90},"medium":{"url":"https://i.ytimg.com/vi/kPDV5p1CcGk/mqdefault.jpg","width":320,"height":180},"high":{"url":"https://i.ytimg.com/vi/kPDV5p1CcGk/hqdefault.jpg","width":480,"height":360},"standard":{"url":"https://i.ytimg.com/vi/kPDV5p1CcGk/sddefault.jpg","width":640,"height":480},"maxres":{"url":"https://i.ytimg.com/vi/kPDV5p1CcGk/maxresdefault.jpg","width":1280,"height":720}},"channelTitle":"Carlos Azaustre - Aprende JavaScript","playlistId":"UUJgGc8pQO1lv04VXrBxA_Hg","position":2,"resourceId":{"kind":"youtube#video","videoId":"kPDV5p1CcGk"},"videoOwnerChannelTitle":"Carlos Azaustre - Aprende JavaScript","videoOwnerChannelId":"UCJgGc8pQO1lv04VXrBxA_Hg"}},{"kind":"youtube#playlistItem","etag":"epKyHvS9_iqm7_Fk_IL9twAgazc","id":"VVVKZ0djOHBRTzFsdjA0VlhyQnhBX0hnLlNpZ1ZWSm1VR3Y4","snippet":{"publishedAt":"2022-11-29T16:23:00Z","channelId":"UCJgGc8pQO1lv04VXrBxA_Hg","title":"Haz tus mensajes de GIT Commit PROFESIONALES con CONVENTIONAL COMMITS","description":"¿Te gustaría mejorar tus mensajes de commit de una manera más semántica, profesional y que te sirva para automatizar ciertas tareas?\nEso lo puedes conseguir con los Conventional Commits, una especificación para dotar de mayor significado y legibilidad al historial de cambios de tu repositorio.\n\nTambién te puede interesar:\nGIT HOOKS: Mejora tu flujo de trabajo con HUSKY y LINT-STAGED\n► https://www.youtube.com/watch?v=YWBrzwSDpo8\n\nÚnete a la MEJOR COMUNIDAD de programación y desarrollo web en español. \n► https://discord.gg/carlosazaustre \n\nSuscríbete y activa la campanita para no perderte ningún vídeo \n► https://youtube.com/carlosazaustre?sub_confirmation=1","thumbnails":{"default":{"url":"https://i.ytimg.com/vi/SigVVJmUGv8/default.jpg","width":120,"height":90},"medium":{"url":"https://i.ytimg.com/vi/SigVVJmUGv8/mqdefault.jpg","width":320,"height":180},"high":{"url":"https://i.ytimg.com/vi/SigVVJmUGv8/hqdefault.jpg","width":480,"height":360},"standard":{"url":"https://i.ytimg.com/vi/SigVVJmUGv8/sddefault.jpg","width":640,"height":480},"maxres":{"url":"https://i.ytimg.com/vi/SigVVJmUGv8/maxresdefault.jpg","width":1280,"height":720}},"channelTitle":"Carlos Azaustre - Aprende JavaScript","playlistId":"UUJgGc8pQO1lv04VXrBxA_Hg","position":3,"resourceId":{"kind":"youtube#video","videoId":"SigVVJmUGv8"},"videoOwnerChannelTitle":"Carlos Azaustre - Aprende JavaScript","videoOwnerChannelId":"UCJgGc8pQO1lv04VXrBxA_Hg"}},{"kind":"youtube#playlistItem","etag":"bp8UdrgFyHaSQtBqQ7Nd9wrHxcQ","id":"VVVKZ0djOHBRTzFsdjA0VlhyQnhBX0hnLmtfblY3RXhRZHc0","snippet":{"publishedAt":"2022-11-28T16:17:00Z","channelId":"UCJgGc8pQO1lv04VXrBxA_Hg","title":"🤔Por esto tienen 3 NÚMEROS las versiones de SOFTWARE","description":"","thumbnails":{"default":{"url":"https://i.ytimg.com/vi/k_nV7ExQdw4/default.jpg","width":120,"height":90},"medium":{"url":"https://i.ytimg.com/vi/k_nV7ExQdw4/mqdefault.jpg","width":320,"height":180},"high":{"url":"https://i.ytimg.com/vi/k_nV7ExQdw4/hqdefault.jpg","width":480,"height":360},"standard":{"url":"https://i.ytimg.com/vi/k_nV7ExQdw4/sddefault.jpg","width":640,"height":480},"maxres":{"url":"https://i.ytimg.com/vi/k_nV7ExQdw4/maxresdefault.jpg","width":1280,"height":720}},"channelTitle":"Carlos Azaustre - Aprende JavaScript","playlistId":"UUJgGc8pQO1lv04VXrBxA_Hg","position":4,"resourceId":{"kind":"youtube#video","videoId":"k_nV7ExQdw4"},"videoOwnerChannelTitle":"Carlos Azaustre - Aprende JavaScript","videoOwnerChannelId":"UCJgGc8pQO1lv04VXrBxA_Hg"}}]